ccr_modules/__init__.py
ccr_modules/common.py
ccr_modules-0.1.5.dist-info/METADATA
ccr_modules-0.1.5.dist-info/WHEEL
ccr_modules-0.1.5.dist-info/entry_points.txt
ccr_modules-0.1.5.dist-info/RECORD
